[
  {
    "class": "img",
    "image": "end-is-near",
    "name": "end is near",
    "version": "A"
  },
  {
    "class": "img-2",
    "image": "dark-words-stain",
    "name": "dark words stain",
    "version": "A"
  },
  {
    "class": "img-2",
    "image": "create-with-pain",
    "name": "create with pain",
    "version": "A"
  },
  {
    "class": "img-2",
    "image": "devil-bets-lose",
    "name": "devil bets lose",
    "version": "A"
  },
  {
    "class": "img",
    "image": "embrace-illuminate-resist",
    "name": "embrace illuminate resist",
    "version": "A"
  },
  {
    "class": "img",
    "image": "eyes-wide-awake",
    "name": "eyes wide awake",
    "version": "A"
  },
  {
    "class": "img-4",
    "image": "amnesia-breeds-repetition",
    "name": "amnesia breeds repetition",
    "version": "A"
  },
  {
    "class": "img",
    "image": "fades-fangs-vanish",
    "name": "fades fangs vanish",
    "version": "A"
  },
  {
    "class": "img-2",
    "image": "healing-through-abandonment",
    "name": "healing through abandonment",
    "version": "A"
  },
  {
    "class": "img",
    "image": "sex-with-cops",
    "name": "sex with cops",
    "version": "A"
  },
  {
    "class": "img",
    "image": "eat-the-rich",
    "name": "eat the rich",
    "version": "A"
  },
  {
    "class": "img",
    "image": "delete-dull-minds",
    "name": "delete dull minds",
    "version": "A"
  },
  {
    "class": "img",
    "image": "defy-ooze-obliterate",
    "name": "defy ooze obliterate",
    "version": "A"
  },
  {
    "class": "img",
    "image": "blossoms-reclaim-concrete",
    "name": "blossoms reclaim concrete",
    "version": "A"
  },
  {
    "class": "img-4",
    "image": "blue-memories-fade",
    "name": "blue memories fade",
    "version": "A"
  },
  {
    "class": "img",
    "image": "joy-conquers-sorrow",
    "name": "joy conquers sorrow",
    "version": "A"
  },
  {
    "class": "img",
    "image": "grind-rise-learn",
    "name": "grind rise learn",
    "version": "A"
  },
  {
    "class": "img",
    "image": "unmask-forgotten-triumphs",
    "name": "unmask forgotten triumphs",
    "version": "A"
  },
  {
    "class": "img",
    "image": "wipe-transform-empower",
    "name": "wipe transform empower",
    "version": "A"
  },
  {
    "class": "img-4",
    "image": "fading-pain-canvas",
    "name": "fading pain canvas",
    "version": "A"
  },
  {
    "class": "img-2",
    "image": "gaps-perpetuate-injustice",
    "name": "gaps perpetuate injustice",
    "version": "A"
  },
  {
    "class": "img",
    "image": "smudged-heartbreak-tales",
    "name": "smudged heartbreak tales",
    "version": "A"
  },
  {
    "class": "img-4",
    "image": "ignorance-to-empathy",
    "name": "ignorance to empathy",
    "version": "A"
  },
  {
    "class": "img",
    "image": "passion-persists-here",
    "name": "passion persists here",
    "version": "A"
  },
  {
    "class": "img-4",
    "image": "kill-the-poor",
    "name": "kill the poor",
    "version": "A"
  },
  {
    "class": "img",
    "image": "promote-positivity-instead",
    "name": "promote positivity instead",
    "version": "A"
  },
  {
    "class": "img",
    "image": "healing-amidst-neglect",
    "name": "healing amidst neglect",
    "version": "A"
  },
  {
    "class": "img-2",
    "image": "forget-me-not",
    "name": "forget me not",
    "version": "A"
  },
  {
    "class": "img",
    "image": "resist-persist-exist",
    "name": "resist persist exist",
    "version": "A"
  },
  {
    "class": "img-2",
    "image": "notes-numb-minds",
    "name": "notes numb minds",
    "version": "A"
  },
  {
    "class": "img-2",
    "image": "embrace-olive-diversity",
    "name": "embrace olive diversity",
    "version": "A"
  },
  {
    "class": "img",
    "image": "preserve-the-untold",
    "name": "preserve the untold",
    "version": "A"
  },
  {
    "class": "img-4",
    "image": "provocative-urban-expression",
    "name": "provocative urban expression",
    "version": "A"
  },
  {
    "class": "img",
    "image": "mindful-mimicry-unleashed",
    "name": "mindful mimicry unleashed",
    "version": "A"
  },
  {
    "class": "img",
    "image": "saving-the-world",
    "name": "saving the world",
    "version": "A"
  },
  {
    "class": "img",
    "image": "purr-power-revolution",
    "name": "purr power revolution",
    "version": "A"
  },
  {
    "class": "img-4",
    "image": "shadow-portal-escape",
    "name": "shadow portal escape",
    "version": "A"
  },
  {
    "class": "img-4",
    "image": "whispers-echo-on",
    "name": "whispers echo on",
    "version": "A"
  },
  {
    "class": "img-4",
    "image": "infernal-blaze-unraveling",
    "name": "infernal blaze unraveling",
    "version": "A"
  },
  {
    "class": "img-2",
    "image": "silent-poison-spreads",
    "name": "silent poison spreads",
    "version": "A"
  },
  {
    "class": "img-4",
    "image": "sow-love-dogma",
    "name": "sow love dogma",
    "version": "A"
  },
  {
    "class": "img-2",
    "image": "stormy-hearts-resist",
    "name": "stormy hearts resist",
    "version": "A"
  },
  {
    "class": "img",
    "image": "no-easy-solutions",
    "name": "no easy solutions",
    "version": "A"
  },
  {
    "class": "img",
    "image": "nights-silent-scream",
    "name": "nights silent scream",
    "version": "A"
  },
  {
    "class": "img",
    "image": "suck-melting-chains",
    "name": "suck melting chains",
    "version": "A"
  },
  {
    "class": "img-4",
    "image": "tears-fuel-art",
    "name": "tears fuel art",
    "version": "A"
  },
  {
    "class": "img-4",
    "image": "void-breeds-division",
    "name": "void breeds division",
    "version": "A"
  },
  {
    "class": "img",
    "image": "whispers-fade-away",
    "name": "whispers fade away",
    "version": "A"
  },
  {
    "class": "img-2",
    "image": "warning-toxic-glow",
    "name": "warning toxic glow",
    "version": "A"
  },
  {
    "class": "img-2",
    "image": "whispers-conceal-truth",
    "name": "whispers conceal truth",
    "version": "A"
  }
]
